smtpbench/__init__.py
smtpbench/__main__.py
smtpbench/cli.py
smtpbench-1.1.0.dist-info/licenses/LICENSE
smtpbench-1.1.0.dist-info/METADATA
smtpbench-1.1.0.dist-info/WHEEL
smtpbench-1.1.0.dist-info/entry_points.txt
smtpbench-1.1.0.dist-info/top_level.txt
smtpbench-1.1.0.dist-info/RECORD
