Metadata-Version: 2.4
Name: smtpbench
Version: 1.1.0
Summary: A robust SMTP load testing and benchmarking tool with MX failover and detailed logging
Author-email: Randall Morse <rmorse@lets.qa>
Maintainer-email: Randall Morse <rmorse@lets.qa>
License: MIT
Project-URL: Homepage, https://github.com/SMTPBench/SMTPBench
Project-URL: Documentation, https://github.com/SMTPBench/SMTPBench#readme
Project-URL: Repository, https://github.com/SMTPBench/SMTPBench
Project-URL: Issues, https://github.com/SMTPBench/SMTPBench/issues
Keywords: smtp,email,load-testing,testing,performance,benchmark,benchmarking
Classifier: Development Status :: 4 - Beta
Classifier: Intended Audience :: Developers
Classifier: Intended Audience :: System Administrators
Classifier: Topic :: Communications :: Email
Classifier: Topic :: Software Development :: Testing
Classifier: License :: OSI Approved :: MIT License
Classifier: Programming Language :: Python :: 3
Classifier: Programming Language :: Python :: 3.8
Classifier: Programming Language :: Python :: 3.9
Classifier: Programming Language :: Python :: 3.10
Classifier: Programming Language :: Python :: 3.11
Classifier: Programming Language :: Python :: 3.12
Requires-Python: >=3.8
License-File: LICENSE
Requires-Dist: dnspython>=2.0.0
Requires-Dist: tqdm>=4.0.0
Requires-Dist: colorama>=0.4.0
Dynamic: license-file
